transphire_transform/__init__.py
transphire_transform/dump_load/__init__.py
transphire_transform/dump_load/box.py
transphire_transform/dump_load/cter.py
transphire_transform/dump_load/ctffind.py
transphire_transform/dump_load/motioncor2.py
transphire_transform/dump_load/mrc.py
transphire_transform/dump_load/star.py
transphire_transform/dump_load/unblur.py
transphire_transform/dump_load/util.py
transphire_transform/dump_load/xml.py
transphire_transform/dump_load/keys/star_keys_relion_2.txt
transphire_transform/dump_load/keys/star_keys_relion_3.txt
transphire_transform/dump_load/tests/__init__.py
transphire_transform/dump_load/tests/test_box.py
transphire_transform/dump_load/tests/test_cter.py
transphire_transform/dump_load/tests/test_ctffind.py
transphire_transform/dump_load/tests/test_motioncor2.py
transphire_transform/dump_load/tests/test_mrc.py
transphire_transform/dump_load/tests/test_star.py
transphire_transform/dump_load/tests/test_unblur.py
transphire_transform/dump_load/tests/test_util.py
transphire_transform/dump_load/tests/test_xml.py
transphire_transform-0.0.3.dist-info/LICENSE
transphire_transform-0.0.3.dist-info/METADATA
transphire_transform-0.0.3.dist-info/WHEEL
transphire_transform-0.0.3.dist-info/entry_points.txt
transphire_transform-0.0.3.dist-info/top_level.txt
transphire_transform-0.0.3.dist-info/RECORD
