Metadata-Version: 2.1
Name: transphire-transform
Version: 0.0.3
Summary: Utilites to change between SPHIRE, RELION and to modify the data
Home-page: https://github.com/MPI-Dortmund/transphire_transform
Author: Markus Stabrin
Author-email: markus.stabrin@tu-dortmund.de
License: MIT
Platform: UNKNOWN
Classifier: Programming Language :: Python :: 3.7
Classifier: License :: OSI Approved
Classifier: Operating System :: POSIX
Classifier: Operating System :: Unix
Classifier: Operating System :: MacOS
Classifier: Development Status :: 4 - Beta
Requires-Python: ~=3.7
Requires-Dist: pandas (<0.24.0,>=0.23.0)
Requires-Dist: mrcfile (<1.1.0,>=1.0.4)
